pyjson5/__init__.py
pyjson5/__init__.pyi
pyjson5/py.typed
pyjson5/pyjson5.cpython-314-arm-linux-musleabihf.so
pyjson5.libs/libgcc_s-94ee217b.so.1
pyjson5.libs/libstdc++-eac7a817.so.6.0.33
pyjson5-2.0.0.dist-info/METADATA
pyjson5-2.0.0.dist-info/WHEEL
pyjson5-2.0.0.dist-info/top_level.txt
pyjson5-2.0.0.dist-info/RECORD
pyjson5-2.0.0.dist-info/licenses/LICENSE.Apache
pyjson5-2.0.0.dist-info/licenses/LICENSE.MIT
